lcsvec-0.0.1.dist-info/RECORD
lcsvec-0.0.1.dist-info/entry_points.txt
lcsvec-0.0.1.dist-info/METADATA
lcsvec-0.0.1.dist-info/WHEEL
lcsvec-0.0.1.dist-info/licenses/LICENSE
lcsvec/__init__.py
lcsvec/lcs_bind.pyi
lcsvec/lcsvec_ext.cpython-38-x86_64-linux-gnu.so
