Metadata-Version: 2.1
Name: lcsvec
Version: 0.0.1
Summary: Longest Common Subsequence (LCS) extension for vectors.
Keywords: lcs
Author: Nathan Fradet
Maintainer: Nathan Fradet
License:                                  Apache License
Classifier: Development Status :: 3 - Alpha
Classifier: Programming Language :: C++
Classifier: Programming Language :: Python
Classifier: Intended Audience :: Developers
Classifier: Intended Audience :: Science/Research
Classifier: Topic :: Scientific/Engineering :: Artificial Intelligence
Classifier: License :: OSI Approved :: Apache Software License
Classifier: Programming Language :: Python :: 3 :: Only
Classifier: Programming Language :: Python :: 3.8
Classifier: Programming Language :: Python :: 3.9
Classifier: Programming Language :: Python :: 3.10
Classifier: Programming Language :: Python :: 3.11
Classifier: Programming Language :: Python :: 3.12
Classifier: Operating System :: MacOS
Classifier: Operating System :: Microsoft :: Windows
Classifier: Operating System :: POSIX
Classifier: Operating System :: Unix
Project-URL: Homepage, https://github.com/Natooz/LCSvec
Project-URL: Repository, https://github.com/Natooz/LCSvec
Project-URL: Issues, https://github.com/Natooz/LCSvec/issues
Requires-Python: >=3.8
Provides-Extra: test
Provides-Extra: dev
Requires-Dist: pytest-cov; extra == "test"
Requires-Dist: pytest-xdist[psutil]; extra == "test"
Requires-Dist: numpy; extra == "test"
Requires-Dist: torch; extra == "test"
Requires-Dist: pytest-cov; extra == "dev"
Requires-Dist: pytest-xdist[psutil]; extra == "dev"
Requires-Dist: numpy; extra == "dev"
Requires-Dist: torch; extra == "dev"
Requires-Dist: pre-commit; extra == "dev"
